isdcclient.py
isdc_client-1.1.dist-info/LICENSE.txt
isdc_client-1.1.dist-info/METADATA
isdc_client-1.1.dist-info/WHEEL
isdc_client-1.1.dist-info/top_level.txt
isdc_client-1.1.dist-info/RECORD
